{"contributors": null, "truncated": false, "text": "@realDonaldTrump \nLyin' moron. https://t.co/tG8XISt0s7", "is_quote_status": false, "in_reply_to_status_id": null, "id": 946003480958980096, "favorite_count": 0, "entities": {"symbols": [], "user_mentions": [{"id": 25073877, "indices": [0, 16], "id_str": "25073877", "screen_name": "realDonaldTrump", "name": "Donald J. Trump"}], "hashtags": [], "urls": [], "media": [{"expanded_url": "https://twitter.com/PBeotch/status/946003480958980096/photo/1", "display_url": "pic.twitter.com/tG8XISt0s7", "url": "https://t.co/tG8XISt0s7", "media_url_https": "https://pbs.twimg.com/media/DSDhJqXX4AEgygH.jpg", "id_str": "946003477855199233", "sizes": {"large": {"h": 540, "resize": "fit", "w": 540}, "small": {"h": 540, "resize": "fit", "w": 540}, "medium": {"h": 540, "resize": "fit", "w": 540}, "thumb": {"h": 150, "resize": "crop", "w": 150}}, "indices": [31, 54], "type": "photo", "id": 946003477855199233, "media_url": "http://pbs.twimg.com/media/DSDhJqXX4AEgygH.jpg"}]}, "retweeted": false, "coordinates": null, "source": "<a href=\"http://twitter.com/download/android\" rel=\"nofollow\">Twitter for Android</a>", "in_reply_to_screen_name": "realDonaldTrump", "in_reply_to_user_id": 25073877, "retweet_count": 0, "id_str": "946003480958980096", "favorited": false, "user": {"follow_request_sent": false, "has_extended_profile": true, "profile_use_background_image": false, "default_profile_image": false, "id": 868600469140230144, "profile_background_image_url_https": "https://abs.twimg.com/images/themes/theme1/bg.png", "verified": false, "translator_type": "none", "profile_text_color": "000000", "profile_image_url_https": "https://pbs.twimg.com/profile_images/916362332275658752/6t5jqbeS_normal.jpg", "profile_sidebar_fill_color": "000000", "entities": {"description": {"urls": []}}, "followers_count": 1152, "profile_sidebar_border_color": "000000", "id_str": "868600469140230144", "profile_background_color": "000000", "listed_count": 2, "is_translation_enabled": false, "utc_offset": -18000, "statuses_count": 7604, "description": "All filters off when it comes to Trump. You might not like my language but I don't care. Browns fan since I was a kid (somebody's gotta like 'em) \n#Resist #FBR", "friends_count": 1488, "location": "West Virginia, USA", "profile_link_color": "19CF86", "profile_image_url": "http://pbs.twimg.com/profile_images/916362332275658752/6t5jqbeS_normal.jpg", "following": false, "geo_enabled": false, "profile_banner_url": "https://pbs.twimg.com/profile_banners/868600469140230144/1500770404", "profile_background_image_url": "http://abs.twimg.com/images/themes/theme1/bg.png", "screen_name": "PBeotch", "lang": "en", "profile_background_tile": false, "favourites_count": 3824, "name": "\ud83c\udf0aPutin's Beotch\ud83c\udf0a", "notifications": false, "url": null, "created_at": "Sat May 27 22:51:04 +0000 2017", "contributors_enabled": false, "time_zone": "Eastern Time (US & Canada)", "protected": false, "default_profile": false, "is_translator": false}, "geo": null, "in_reply_to_user_id_str": "25073877", "possibly_sensitive": false, "lang": "en", "created_at": "Wed Dec 27 13:03:00 +0000 2017", "in_reply_to_status_id_str": null, "place": null, "extended_entities": {"media": [{"expanded_url": "https://twitter.com/PBeotch/status/946003480958980096/photo/1", "display_url": "pic.twitter.com/tG8XISt0s7", "url": "https://t.co/tG8XISt0s7", "media_url_https": "https://pbs.twimg.com/media/DSDhJqXX4AEgygH.jpg", "id_str": "946003477855199233", "sizes": {"large": {"h": 540, "resize": "fit", "w": 540}, "small": {"h": 540, "resize": "fit", "w": 540}, "medium": {"h": 540, "resize": "fit", "w": 540}, "thumb": {"h": 150, "resize": "crop", "w": 150}}, "indices": [31, 54], "type": "photo", "id": 946003477855199233, "media_url": "http://pbs.twimg.com/media/DSDhJqXX4AEgygH.jpg"}]}, "metadata": {"iso_language_code": "en", "result_type": "recent"}}