{"contributors": null, "truncated": true, "text": "@realDonaldTrump Love you both! Merry Christmas to POTUS &amp; FLOTUS &amp; Barron Too! We Love our First Family of Trump t\u2026 https://t.co/RBZcXcj12F", "is_quote_status": false, "in_reply_to_status_id": 945287222210781184, "id": 946003070772744192, "favorite_count": 0, "entities": {"symbols": [], "user_mentions": [{"id": 25073877, "indices": [0, 16], "id_str": "25073877", "screen_name": "realDonaldTrump", "name": "Donald J. Trump"}], "hashtags": [], "urls": [{"url": "https://t.co/RBZcXcj12F", "indices": [125, 148], "expanded_url": "https://twitter.com/i/web/status/946003070772744192", "display_url": "twitter.com/i/web/status/9\u2026"}]}, "retweeted": false, "coordinates": null, "source": "<a href=\"http://twitter.com/download/iphone\" rel=\"nofollow\">Twitter for iPhone</a>", "in_reply_to_screen_name": "realDonaldTrump", "in_reply_to_user_id": 25073877, "retweet_count": 0, "id_str": "946003070772744192", "favorited": false, "user": {"follow_request_sent": false, "has_extended_profile": false, "profile_use_background_image": true, "default_profile_image": false, "id": 487222556, "profile_background_image_url_https": "https://abs.twimg.com/images/themes/theme1/bg.png", "verified": false, "translator_type": "none", "profile_text_color": "333333", "profile_image_url_https": "https://pbs.twimg.com/profile_images/920688737364869120/QgguRSwm_normal.jpg", "profile_sidebar_fill_color": "DDEEF6", "entities": {"description": {"urls": []}}, "followers_count": 738, "profile_sidebar_border_color": "C0DEED", "id_str": "487222556", "profile_background_color": "C0DEED", "listed_count": 23, "is_translation_enabled": false, "utc_offset": null, "statuses_count": 20116, "description": "Patriot wife mother Artist OC fan love Trump & USA!", "friends_count": 998, "location": "Maryland, USA", "profile_link_color": "1DA1F2", "profile_image_url": "http://pbs.twimg.com/profile_images/920688737364869120/QgguRSwm_normal.jpg", "following": false, "geo_enabled": true, "profile_background_image_url": "http://abs.twimg.com/images/themes/theme1/bg.png", "screen_name": "SissyScullen", "lang": "en", "profile_background_tile": false, "favourites_count": 12748, "name": "Carol Darling", "notifications": false, "url": null, "created_at": "Thu Feb 09 04:11:09 +0000 2012", "contributors_enabled": false, "time_zone": null, "protected": false, "default_profile": true, "is_translator": false}, "geo": null, "in_reply_to_user_id_str": "25073877", "lang": "en", "created_at": "Wed Dec 27 13:01:22 +0000 2017", "in_reply_to_status_id_str": "945287222210781184", "place": {"full_name": "Aspen Hill, MD", "url": "https://api.twitter.com/1.1/geo/id/08d254a18a834e3f.json", "country": "United States", "place_type": "city", "bounding_box": {"type": "Polygon", "coordinates": [[[-77.125438, 39.059951], [-77.0338, 39.059951], [-77.0338, 39.120903], [-77.125438, 39.120903]]]}, "contained_within": [], "country_code": "US", "attributes": {}, "id": "08d254a18a834e3f", "name": "Aspen Hill"}, "metadata": {"iso_language_code": "en", "result_type": "recent"}}