{"contributors": null, "truncated": false, "text": "RT @jptoner50: As @SpeakerRyan @SenateMajLdr and @realDonaldTrump look to roll back entitlements, they will push hard to eliminate the #SNA\u2026", "is_quote_status": false, "in_reply_to_status_id": null, "id": 946011239720869888, "favorite_count": 0, "entities": {"symbols": [], "user_mentions": [{"id": 19516513, "indices": [3, 13], "id_str": "19516513", "screen_name": "jptoner50", "name": "John Toner"}, {"id": 18916432, "indices": [18, 30], "id_str": "18916432", "screen_name": "SpeakerRyan", "name": "Paul Ryan"}, {"id": 1249982359, "indices": [31, 44], "id_str": "1249982359", "screen_name": "SenateMajLdr", "name": "Leader McConnell"}, {"id": 25073877, "indices": [49, 65], "id_str": "25073877", "screen_name": "realDonaldTrump", "name": "Donald J. Trump"}], "hashtags": [], "urls": []}, "retweeted": false, "coordinates": null, "source": "<a href=\"http://twitter.com/download/iphone\" rel=\"nofollow\">Twitter for iPhone</a>", "in_reply_to_screen_name": null, "in_reply_to_user_id": null, "retweet_count": 174, "id_str": "946011239720869888", "favorited": false, "retweeted_status": {"contributors": null, "truncated": true, "text": "As @SpeakerRyan @SenateMajLdr and @realDonaldTrump look to roll back entitlements, they will push hard to eliminate\u2026 https://t.co/NBHx6cTvKV", "is_quote_status": false, "in_reply_to_status_id": null, "id": 945997583553581056, "favorite_count": 168, "entities": {"symbols": [], "user_mentions": [{"id": 18916432, "indices": [3, 15], "id_str": "18916432", "screen_name": "SpeakerRyan", "name": "Paul Ryan"}, {"id": 1249982359, "indices": [16, 29], "id_str": "1249982359", "screen_name": "SenateMajLdr", "name": "Leader McConnell"}, {"id": 25073877, "indices": [34, 50], "id_str": "25073877", "screen_name": "realDonaldTrump", "name": "Donald J. Trump"}], "hashtags": [], "urls": [{"url": "https://t.co/NBHx6cTvKV", "indices": [117, 140], "expanded_url": "https://twitter.com/i/web/status/945997583553581056", "display_url": "twitter.com/i/web/status/9\u2026"}]}, "retweeted": false, "coordinates": null, "source": "<a href=\"http://bufferapp.com\" rel=\"nofollow\">Buffer</a>", "in_reply_to_screen_name": null, "in_reply_to_user_id": null, "retweet_count": 174, "id_str": "945997583553581056", "favorited": false, "user": {"follow_request_sent": false, "has_extended_profile": false, "profile_use_background_image": true, "default_profile_image": false, "id": 19516513, "profile_background_image_url_https": "https://pbs.twimg.com/profile_background_images/197688633/starrynight_52_42495.jpg", "verified": false, "translator_type": "none", "profile_text_color": "63A0BA", "profile_image_url_https": "https://pbs.twimg.com/profile_images/945479029498499072/YbWhwnnr_normal.jpg", "profile_sidebar_fill_color": "053343", "entities": {"description": {"urls": []}}, "followers_count": 5405, "profile_sidebar_border_color": "1A1A1E", "id_str": "19516513", "profile_background_color": "053343", "listed_count": 85, "is_translation_enabled": false, "utc_offset": -18000, "statuses_count": 9999, "description": "I believe in facts, compassion, equal rights, and that everyone has value. Blue Hen for life! #TheResistance #UnitedBlue #NeverTrump I follow back.", "friends_count": 5273, "location": "Bethlehem, PA", "profile_link_color": "2FC2EF", "profile_image_url": "http://pbs.twimg.com/profile_images/945479029498499072/YbWhwnnr_normal.jpg", "following": false, "geo_enabled": true, "profile_banner_url": "https://pbs.twimg.com/profile_banners/19516513/1499227796", "profile_background_image_url": "http://pbs.twimg.com/profile_background_images/197688633/starrynight_52_42495.jpg", "screen_name": "jptoner50", "lang": "en", "profile_background_tile": true, "favourites_count": 1520, "name": "John Toner", "notifications": false, "url": null, "created_at": "Mon Jan 26 02:24:19 +0000 2009", "contributors_enabled": false, "time_zone": "Eastern Time (US & Canada)", "protected": false, "default_profile": false, "is_translator": false}, "geo": null, "in_reply_to_user_id_str": null, "possibly_sensitive": false, "lang": "en", "created_at": "Wed Dec 27 12:39:34 +0000 2017", "in_reply_to_status_id_str": null, "place": null, "metadata": {"iso_language_code": "en", "result_type": "recent"}}, "user": {"follow_request_sent": false, "has_extended_profile": false, "profile_use_background_image": true, "default_profile_image": false, "id": 773854912778276864, "profile_background_image_url_https": null, "verified": false, "translator_type": "none", "profile_text_color": "333333", "profile_image_url_https": "https://pbs.twimg.com/profile_images/930061524726673408/NyvOCfUZ_normal.jpg", "profile_sidebar_fill_color": "DDEEF6", "entities": {"description": {"urls": []}}, "followers_count": 906, "profile_sidebar_border_color": "C0DEED", "id_str": "773854912778276864", "profile_background_color": "F5F8FA", "listed_count": 3, "is_translation_enabled": false, "utc_offset": null, "statuses_count": 58165, "description": "Qigong Energy Therapist & Nonprofit Consultant. #the resistance", "friends_count": 1272, "location": "", "profile_link_color": "1DA1F2", "profile_image_url": "http://pbs.twimg.com/profile_images/930061524726673408/NyvOCfUZ_normal.jpg", "following": false, "geo_enabled": true, "profile_banner_url": "https://pbs.twimg.com/profile_banners/773854912778276864/1496319902", "profile_background_image_url": null, "screen_name": "uptownmelissa", "lang": "en", "profile_background_tile": false, "favourites_count": 105553, "name": "Melissa", "notifications": false, "url": null, "created_at": "Thu Sep 08 12:06:03 +0000 2016", "contributors_enabled": false, "time_zone": null, "protected": false, "default_profile": true, "is_translator": false}, "geo": null, "in_reply_to_user_id_str": null, "lang": "en", "created_at": "Wed Dec 27 13:33:50 +0000 2017", "in_reply_to_status_id_str": null, "place": null, "metadata": {"iso_language_code": "en", "result_type": "recent"}}