{"contributors": null, "truncated": false, "text": "@Jerusalem_Post @realDonaldTrump @Israel_katz  https://t.co/e8LuMnXt9I", "is_quote_status": false, "in_reply_to_status_id": 945935169210503169, "id": 946018057742356480, "favorite_count": 2, "entities": {"symbols": [], "user_mentions": [{"id": 19489239, "indices": [0, 15], "id_str": "19489239", "screen_name": "Jerusalem_Post", "name": "The Jerusalem Post"}, {"id": 25073877, "indices": [16, 32], "id_str": "25073877", "screen_name": "realDonaldTrump", "name": "Donald J. Trump"}, {"id": 804249337672908800, "indices": [33, 45], "id_str": "804249337672908800", "screen_name": "Israel_katz", "name": "\u05d9\u05e9\u05e8\u05d0\u05dc \u05db\u05e5 Israel Katz"}], "hashtags": [], "urls": [], "media": [{"expanded_url": "https://twitter.com/EJ_Riv/status/946018057742356480/photo/1", "display_url": "pic.twitter.com/e8LuMnXt9I", "url": "https://t.co/e8LuMnXt9I", "media_url_https": "https://pbs.twimg.com/tweet_video_thumb/DSDuZsyUIAYNnAn.jpg", "id_str": "946018047034138630", "sizes": {"small": {"h": 152, "resize": "fit", "w": 200}, "large": {"h": 152, "resize": "fit", "w": 200}, "medium": {"h": 152, "resize": "fit", "w": 200}, "thumb": {"h": 150, "resize": "crop", "w": 150}}, "indices": [47, 70], "type": "photo", "id": 946018047034138630, "media_url": "http://pbs.twimg.com/tweet_video_thumb/DSDuZsyUIAYNnAn.jpg"}]}, "retweeted": false, "coordinates": null, "source": "<a href=\"http://twitter.com\" rel=\"nofollow\">Twitter Web Client</a>", "in_reply_to_screen_name": "Jerusalem_Post", "in_reply_to_user_id": 19489239, "retweet_count": 0, "id_str": "946018057742356480", "favorited": false, "user": {"follow_request_sent": false, "has_extended_profile": false, "profile_use_background_image": true, "default_profile_image": false, "id": 327021199, "profile_background_image_url_https": "https://pbs.twimg.com/profile_background_images/378800000079315300/045f5a77f5fc19641fd8ebdd53f98aba.jpeg", "verified": false, "translator_type": "none", "profile_text_color": "3D1957", "profile_image_url_https": "https://pbs.twimg.com/profile_images/821187436726390784/DGkeiP9O_normal.jpg", "profile_sidebar_fill_color": "7AC3EE", "entities": {"description": {"urls": []}}, "followers_count": 298, "profile_sidebar_border_color": "FFFFFF", "id_str": "327021199", "profile_background_color": "1A1B1F", "listed_count": 9, "is_translation_enabled": false, "utc_offset": -28800, "statuses_count": 10793, "description": "Normally, small talk is enough for me to form an opinion of someone. I make quick judgments, often completely wrong, and then stick by them rigidly.", "friends_count": 626, "location": "", "profile_link_color": "2FC2EF", "profile_image_url": "http://pbs.twimg.com/profile_images/821187436726390784/DGkeiP9O_normal.jpg", "following": false, "geo_enabled": true, "profile_banner_url": "https://pbs.twimg.com/profile_banners/327021199/1484621660", "profile_background_image_url": "http://pbs.twimg.com/profile_background_images/378800000079315300/045f5a77f5fc19641fd8ebdd53f98aba.jpeg", "screen_name": "EJ_Riv", "lang": "en", "profile_background_tile": true, "favourites_count": 2354, "name": "Flea J", "notifications": false, "url": null, "created_at": "Thu Jun 30 21:34:09 +0000 2011", "contributors_enabled": false, "time_zone": "Pacific Time (US & Canada)", "protected": false, "default_profile": false, "is_translator": false}, "geo": null, "in_reply_to_user_id_str": "19489239", "possibly_sensitive": false, "lang": "und", "created_at": "Wed Dec 27 14:00:55 +0000 2017", "in_reply_to_status_id_str": "945935169210503169", "place": null, "extended_entities": {"media": [{"expanded_url": "https://twitter.com/EJ_Riv/status/946018057742356480/photo/1", "display_url": "pic.twitter.com/e8LuMnXt9I", "url": "https://t.co/e8LuMnXt9I", "media_url_https": "https://pbs.twimg.com/tweet_video_thumb/DSDuZsyUIAYNnAn.jpg", "video_info": {"aspect_ratio": [25, 19], "variants": [{"url": "https://video.twimg.com/tweet_video/DSDuZsyUIAYNnAn.mp4", "bitrate": 0, "content_type": "video/mp4"}]}, "id_str": "946018047034138630", "sizes": {"small": {"h": 152, "resize": "fit", "w": 200}, "large": {"h": 152, "resize": "fit", "w": 200}, "medium": {"h": 152, "resize": "fit", "w": 200}, "thumb": {"h": 150, "resize": "crop", "w": 150}}, "indices": [47, 70], "type": "animated_gif", "id": 946018047034138630, "media_url": "http://pbs.twimg.com/tweet_video_thumb/DSDuZsyUIAYNnAn.jpg"}]}, "metadata": {"iso_language_code": "und", "result_type": "recent"}}