{"contributors": null, "truncated": true, "text": "@GOVUK... Do you really want an alleged leader who makes fun of people with disabilities at Harry's wedding? If you\u2026 https://t.co/C8eq6wYaFL", "is_quote_status": true, "in_reply_to_status_id": null, "id": 946022883364605952, "favorite_count": 0, "entities": {"symbols": [], "user_mentions": [{"id": 17481977, "indices": [0, 6], "id_str": "17481977", "screen_name": "GOVUK", "name": "GOV UK"}], "hashtags": [], "urls": [{"url": "https://t.co/C8eq6wYaFL", "indices": [117, 140], "expanded_url": "https://twitter.com/i/web/status/946022883364605952", "display_url": "twitter.com/i/web/status/9\u2026"}]}, "quoted_status_id": 945997950622273536, "retweeted": false, "coordinates": null, "quoted_status": {"contributors": null, "truncated": false, "text": "@Resistance_Feed Its ok, the \ud83c\udf0eunderstands if you don't want this \ud83d\udc47at your wedding. https://t.co/Ezg9khkvmG", "is_quote_status": false, "in_reply_to_status_id": 945995923431161856, "id": 945997950622273536, "favorite_count": 12, "entities": {"symbols": [], "user_mentions": [{"id": 4437493517, "indices": [0, 16], "id_str": "4437493517", "screen_name": "Resistance_Feed", "name": "The Resistance"}], "hashtags": [], "urls": [], "media": [{"expanded_url": "https://twitter.com/BaconJoel/status/945997950622273536/photo/1", "display_url": "pic.twitter.com/Ezg9khkvmG", "url": "https://t.co/Ezg9khkvmG", "media_url_https": "https://pbs.twimg.com/tweet_video_thumb/DSDcE7rWkAEAdo9.jpg", "id_str": "945997899044917249", "sizes": {"large": {"h": 180, "resize": "fit", "w": 320}, "small": {"h": 180, "resize": "fit", "w": 320}, "medium": {"h": 180, "resize": "fit", "w": 320}, "thumb": {"h": 150, "resize": "crop", "w": 150}}, "indices": [83, 106], "type": "photo", "id": 945997899044917249, "media_url": "http://pbs.twimg.com/tweet_video_thumb/DSDcE7rWkAEAdo9.jpg"}]}, "retweeted": false, "coordinates": null, "source": "<a href=\"http://twitter.com/download/android\" rel=\"nofollow\">Twitter for Android</a>", "in_reply_to_screen_name": "Resistance_Feed", "in_reply_to_user_id": 4437493517, "retweet_count": 1, "id_str": "945997950622273536", "favorited": false, "user": {"follow_request_sent": false, "has_extended_profile": false, "profile_use_background_image": true, "default_profile_image": false, "id": 497468210, "profile_background_image_url_https": "https://abs.twimg.com/images/themes/theme1/bg.png", "verified": false, "translator_type": "none", "profile_text_color": "333333", "profile_image_url_https": "https://pbs.twimg.com/profile_images/739561742057885697/GKSgtVEh_normal.jpg", "profile_sidebar_fill_color": "DDEEF6", "entities": {"description": {"urls": []}}, "followers_count": 1102, "profile_sidebar_border_color": "C0DEED", "id_str": "497468210", "profile_background_color": "C0DEED", "listed_count": 9, "is_translation_enabled": false, "utc_offset": -18000, "statuses_count": 11545, "description": "Environment", "friends_count": 5001, "location": "OCCUPIED USA SOS", "profile_link_color": "1DA1F2", "profile_image_url": "http://pbs.twimg.com/profile_images/739561742057885697/GKSgtVEh_normal.jpg", "following": false, "geo_enabled": false, "profile_banner_url": "https://pbs.twimg.com/profile_banners/497468210/1470836301", "profile_background_image_url": "http://abs.twimg.com/images/themes/theme1/bg.png", "screen_name": "BaconJoel", "lang": "en", "profile_background_tile": false, "favourites_count": 24826, "name": "Rule of Law", "notifications": false, "url": null, "created_at": "Mon Feb 20 01:18:56 +0000 2012", "contributors_enabled": false, "time_zone": "America/New_York", "protected": false, "default_profile": true, "is_translator": false}, "geo": null, "in_reply_to_user_id_str": "4437493517", "possibly_sensitive": true, "lang": "en", "created_at": "Wed Dec 27 12:41:01 +0000 2017", "in_reply_to_status_id_str": "945995923431161856", "place": null, "extended_entities": {"media": [{"expanded_url": "https://twitter.com/BaconJoel/status/945997950622273536/photo/1", "display_url": "pic.twitter.com/Ezg9khkvmG", "url": "https://t.co/Ezg9khkvmG", "media_url_https": "https://pbs.twimg.com/tweet_video_thumb/DSDcE7rWkAEAdo9.jpg", "video_info": {"aspect_ratio": [16, 9], "variants": [{"url": "https://video.twimg.com/tweet_video/DSDcE7rWkAEAdo9.mp4", "bitrate": 0, "content_type": "video/mp4"}]}, "id_str": "945997899044917249", "sizes": {"large": {"h": 180, "resize": "fit", "w": 320}, "small": {"h": 180, "resize": "fit", "w": 320}, "medium": {"h": 180, "resize": "fit", "w": 320}, "thumb": {"h": 150, "resize": "crop", "w": 150}}, "indices": [83, 106], "type": "animated_gif", "id": 945997899044917249, "media_url": "http://pbs.twimg.com/tweet_video_thumb/DSDcE7rWkAEAdo9.jpg"}]}, "metadata": {"iso_language_code": "en", "result_type": "recent"}}, "source": "<a href=\"https://mobile.twitter.com\" rel=\"nofollow\">Twitter Lite</a>", "in_reply_to_screen_name": "GOVUK", "in_reply_to_user_id": 17481977, "retweet_count": 0, "id_str": "946022883364605952", "favorited": false, "user": {"follow_request_sent": false, "has_extended_profile": false, "profile_use_background_image": true, "default_profile_image": false, "id": 25269118, "profile_background_image_url_https": "https://abs.twimg.com/images/themes/theme9/bg.gif", "verified": false, "translator_type": "none", "profile_text_color": "666666", "profile_image_url_https": "https://pbs.twimg.com/profile_images/815210030140190720/mdgAsobh_normal.jpg", "profile_sidebar_fill_color": "252429", "entities": {"description": {"urls": []}}, "followers_count": 338, "profile_sidebar_border_color": "181A1E", "id_str": "25269118", "profile_background_color": "1A1B1F", "listed_count": 0, "is_translation_enabled": false, "utc_offset": -18000, "statuses_count": 15884, "description": "entrepreneur \u2022 engineer \u2022 futurist \u2022 dad \u2022 husband \u2022 environmentalist \u2022 photographer. All posts political to protect & evolve humankind. #TheResistance\nNO LISTS", "friends_count": 905, "location": "Phoenix AZ", "profile_link_color": "2FC2EF", "profile_image_url": "http://pbs.twimg.com/profile_images/815210030140190720/mdgAsobh_normal.jpg", "following": false, "geo_enabled": false, "profile_banner_url": "https://pbs.twimg.com/profile_banners/25269118/1487891315", "profile_background_image_url": "http://abs.twimg.com/images/themes/theme9/bg.gif", "screen_name": "XDaneelOlivaw", "lang": "en", "profile_background_tile": false, "favourites_count": 9274, "name": "XDaneelOlivaw", "notifications": false, "url": null, "created_at": "Thu Mar 19 10:55:28 +0000 2009", "contributors_enabled": false, "time_zone": "Eastern Time (US & Canada)", "protected": false, "default_profile": false, "is_translator": false}, "geo": null, "in_reply_to_user_id_str": "17481977", "possibly_sensitive": false, "lang": "en", "created_at": "Wed Dec 27 14:20:06 +0000 2017", "quoted_status_id_str": "945997950622273536", "in_reply_to_status_id_str": null, "place": null, "metadata": {"iso_language_code": "en", "result_type": "recent"}}