{"contributors": null, "truncated": true, "text": "@pedromf60 @realDonaldTrump Estava a caminhar para l\u00e1, queres um gr\u00e1fico do aumento da d\u00edvida externa dos estados u\u2026 https://t.co/HBObJNaovV", "is_quote_status": false, "in_reply_to_status_id": 946005282613792769, "id": 946016213527908353, "favorite_count": 1, "entities": {"symbols": [], "user_mentions": [{"id": 826218171485011968, "indices": [0, 10], "id_str": "826218171485011968", "screen_name": "pedromf60", "name": "pedro \ud83d\udc94"}, {"id": 25073877, "indices": [11, 27], "id_str": "25073877", "screen_name": "realDonaldTrump", "name": "Donald J. Trump"}], "hashtags": [], "urls": [{"url": "https://t.co/HBObJNaovV", "indices": [117, 140], "expanded_url": "https://twitter.com/i/web/status/946016213527908353", "display_url": "twitter.com/i/web/status/9\u2026"}]}, "retweeted": false, "coordinates": null, "source": "<a href=\"http://twitter.com\" rel=\"nofollow\">Twitter Web Client</a>", "in_reply_to_screen_name": "pedromf60", "in_reply_to_user_id": 826218171485011968, "retweet_count": 0, "id_str": "946016213527908353", "favorited": false, "user": {"follow_request_sent": false, "has_extended_profile": true, "profile_use_background_image": false, "default_profile_image": false, "id": 2756482355, "profile_background_image_url_https": "https://abs.twimg.com/images/themes/theme1/bg.png", "verified": false, "translator_type": "none", "profile_text_color": "000000", "profile_image_url_https": "https://pbs.twimg.com/profile_images/944630684374786049/bFA3iqum_normal.jpg", "profile_sidebar_fill_color": "000000", "entities": {"description": {"urls": []}}, "followers_count": 317, "profile_sidebar_border_color": "000000", "id_str": "2756482355", "profile_background_color": "000000", "listed_count": 6, "is_translation_enabled": false, "utc_offset": 0, "statuses_count": 20819, "description": "No fundo n\u00e3o passo de um puto, com mentalidade de Velho do Restelo e a curiosidade incessante de um infante.", "friends_count": 472, "location": "Pyongyang", "profile_link_color": "3B94D9", "profile_image_url": "http://pbs.twimg.com/profile_images/944630684374786049/bFA3iqum_normal.jpg", "following": false, "geo_enabled": false, "profile_banner_url": "https://pbs.twimg.com/profile_banners/2756482355/1505420276", "profile_background_image_url": "http://abs.twimg.com/images/themes/theme1/bg.png", "screen_name": "baeta013", "lang": "pt", "profile_background_tile": false, "favourites_count": 9356, "name": "Baeta", "notifications": false, "url": null, "created_at": "Sun Aug 31 00:01:25 +0000 2014", "contributors_enabled": false, "time_zone": "London", "protected": false, "default_profile": false, "is_translator": false}, "geo": null, "in_reply_to_user_id_str": "826218171485011968", "lang": "pt", "created_at": "Wed Dec 27 13:53:36 +0000 2017", "in_reply_to_status_id_str": "946005282613792769", "place": null, "metadata": {"iso_language_code": "pt", "result_type": "recent"}}